LICENSE
MANIFEST.in
README.md
REQUIREMENTS
setup.py
bin/decrapify
bin/pair-with
datascope_tools/__init__.py
datascope_tools.egg-info/PKG-INFO
datascope_tools.egg-info/SOURCES.txt
datascope_tools.egg-info/dependency_links.txt
datascope_tools.egg-info/not-zip-safe
datascope_tools.egg-info/top_level.txt