Metadata-Version: 1.1
Name: datascope-tools
Version: 0.0.7
Summary: import random.scripts, random.tools, random.ideas
Home-page: https://github.com/datascopeanalytics/datascope-tools
Author: Datascope Analytics
Author-email: github.admin@datascopeanalytics.com
License: MIT
Download-URL: https://github.com/datascopeanalytics/datascope-tools/archives/master
Platform: UNKNOWN
